<?xml version="1.0" encoding="utf-8"?>
<LanguageData>

  <DMP_Proposal.label>外交婚姻提议</DMP_Proposal.label>
  <DMP_Proposal.letterLabel>外交婚姻提议</DMP_Proposal.letterLabel>
  
  <DMP_RandomVisit.label>联姻关键人物求救</DMP_RandomVisit.label>
  <DMP_Rimcities_PACombinedAssault.label>姻亲盟友进攻城市（需要“边缘城市”模组）</DMP_Rimcities_PACombinedAssault.label>
  <DMP_Rimcities_PACombinedDefense.label>姻亲盟友防御城市（需要“边缘城市”模组）</DMP_Rimcities_PACombinedDefense.label>
  <DMP_DynamicDiplomacy_AllianceAgainstPA.label>姻亲盟友被多个派系联合宣战（需要“动态外交”模组）</DMP_DynamicDiplomacy_AllianceAgainstPA.label>

</LanguageData>